Pokebomari/__init__.py
Pokebomari/pokemon.csv
Pokebomari/random_pokemon.py
Pokebomari-1.0.1.dist-info/METADATA
Pokebomari-1.0.1.dist-info/WHEEL
Pokebomari-1.0.1.dist-info/top_level.txt
Pokebomari-1.0.1.dist-info/RECORD
